napari_emd/__init__.py
napari_emd/_reader.py
napari_emd/_widget.py
napari_emd/napari.yaml
napari_emd/_tests/__init__.py
napari_emd/_tests/test_reader.py
napari_emd/_tests/test_widget.py
napari_EMD-0.1.1.dist-info/LICENSE
napari_EMD-0.1.1.dist-info/METADATA
napari_EMD-0.1.1.dist-info/WHEEL
napari_EMD-0.1.1.dist-info/entry_points.txt
napari_EMD-0.1.1.dist-info/top_level.txt
napari_EMD-0.1.1.dist-info/RECORD
